[
{
  "name":"[B"
},
{
  "name":"[C"
},
{
  "name":"[D"
},
{
  "name":"[F"
},
{
  "name":"[I"
},
{
  "name":"[J"
},
{
  "name":"[Ljava.lang.String;"
},
{
  "name":"[Ljavax.management.openmbean.CompositeData;"
},
{
  "name":"[S"
},
{
  "name":"[Z"
},
{
  "name":"ch.qos.logback.classic.encoder.PatternLayoutEncoder",
  "queryAllPublicMethods":true,
  "methods":[{"name":"<init>","parameterTypes":[] }]
},
{
  "name":"ch.qos.logback.classic.joran.SerializedModelConfigurator",
  "methods":[{"name":"<init>","parameterTypes":[] }]
},
{
  "name":"ch.qos.logback.classic.util.DefaultJoranConfigurator",
  "methods":[{"name":"<init>","parameterTypes":[] }]
},
{
  "name":"ch.qos.logback.core.ConsoleAppender",
  "queryAllPublicMethods":true,
  "methods":[{"name":"<init>","parameterTypes":[] }]
},
{
  "name":"ch.qos.logback.core.OutputStreamAppender",
  "methods":[{"name":"setEncoder","parameterTypes":["ch.qos.logback.core.encoder.Encoder"] }]
},
{
  "name":"ch.qos.logback.core.encoder.Encoder",
  "methods":[{"name":"valueOf","parameterTypes":["java.lang.String"] }]
},
{
  "name":"ch.qos.logback.core.encoder.LayoutWrappingEncoder",
  "methods":[{"name":"setParent","parameterTypes":["ch.qos.logback.core.spi.ContextAware"] }]
},
{
  "name":"ch.qos.logback.core.pattern.PatternLayoutEncoderBase",
  "methods":[{"name":"setPattern","parameterTypes":["java.lang.String"] }]
},
{
  "name":"ch.qos.logback.core.spi.ContextAware",
  "methods":[{"name":"valueOf","parameterTypes":["java.lang.String"] }]
},
{
  "name":"com.aquila.mq.jna.MQCD",
  "allDeclaredFields":true,
  "fields":[{"name":"OPTIONS"}, {"name":"STRING_ENCODING"}, {"name":"STRUCTURE_ALIGNMENT"}, {"name":"TYPE_MAPPER"}]
},
{
  "name":"com.aquila.mq.jna.MQCNO",
  "allDeclaredFields":true,
  "fields":[{"name":"OPTIONS"}, {"name":"STRING_ENCODING"}, {"name":"STRUCTURE_ALIGNMENT"}, {"name":"TYPE_MAPPER"}]
},
{
  "name":"com.aquila.mq.jna.MainIBMMQJNA",
  "allDeclaredClasses":true,
  "queryAllDeclaredMethods":true,
  "queryAllPublicMethods":true
},
{
  "name":"com.aquila.mq.jna.MainIBMMQJNATest",
  "allDeclaredFields":true,
  "allDeclaredClasses":true,
  "queryAllDeclaredMethods":true,
  "queryAllPublicMethods":true,
  "queryAllDeclaredConstructors":true,
  "methods":[{"name":"<init>","parameterTypes":[] }, {"name":"testAllOperations","parameterTypes":[] }]
},
{
  "name":"com.aquila.mq.jna.lib.IBMMQJNA",
  "allDeclaredClasses":true,
  "queryAllPublicMethods":true
},
{
  "name":"com.aquila.mq.jna.lib.MQCD",
  "allDeclaredFields":true,
  "allDeclaredClasses":true,
  "queryAllDeclaredMethods":true,
  "queryAllPublicMethods":true,
  "fields":[{"name":"OPTIONS"}, {"name":"STRING_ENCODING"}, {"name":"STRUCTURE_ALIGNMENT"}, {"name":"TYPE_MAPPER"}]
},
{
  "name":"com.aquila.mq.jna.lib.MQCNO",
  "allDeclaredFields":true,
  "allDeclaredClasses":true,
  "queryAllDeclaredMethods":true,
  "queryAllPublicMethods":true,
  "fields":[{"name":"OPTIONS"}, {"name":"STRING_ENCODING"}, {"name":"STRUCTURE_ALIGNMENT"}, {"name":"TYPE_MAPPER"}]
},
{
  "name":"com.aquila.mq.jna.lib.MQCNO$ByReference",
  "allDeclaredClasses":true,
  "queryAllDeclaredMethods":true,
  "queryAllPublicMethods":true
},
{
  "name":"com.aquila.mq.normal.MainIBMMQJNATest",
  "allDeclaredFields":true,
  "allDeclaredClasses":true,
  "queryAllDeclaredMethods":true,
  "queryAllPublicMethods":true,
  "queryAllDeclaredConstructors":true,
  "methods":[{"name":"<init>","parameterTypes":[] }, {"name":"testAllOperations","parameterTypes":[] }]
},
{
  "name":"com.aquila.mq.normal.NormalMQ",
  "allDeclaredClasses":true,
  "queryAllDeclaredMethods":true,
  "queryAllPublicMethods":true
},
{
  "name":"com.aquila.mq.normal.NormalMQTest",
  "allDeclaredFields":true,
  "allDeclaredClasses":true,
  "queryAllDeclaredMethods":true,
  "queryAllPublicMethods":true,
  "queryAllDeclaredConstructors":true,
  "methods":[{"name":"<init>","parameterTypes":[] }, {"name":"testSend","parameterTypes":[] }]
},
{
  "name":"com.aquila.mq.normal.TestNormalMQ",
  "allDeclaredFields":true,
  "allDeclaredClasses":true,
  "queryAllDeclaredMethods":true,
  "queryAllPublicMethods":true,
  "queryAllDeclaredConstructors":true,
  "methods":[{"name":"<init>","parameterTypes":[] }, {"name":"testSend","parameterTypes":[] }]
},
{
  "name":"com.ibm.mq.constants.MQConstants",
  "allPublicFields":true
},
{
  "name":"com.ibm.mq.ese.jmqi.ESEJMQI",
  "methods":[{"name":"<init>","parameterTypes":["com.ibm.mq.jmqi.JmqiEnvironment","int","com.ibm.mq.jmqi.JmqiMQ"] }]
},
{
  "name":"com.ibm.mq.headers.internal.MQMessageWrapper",
  "methods":[{"name":"<init>","parameterTypes":["java.io.DataInput"] }, {"name":"<init>","parameterTypes":["java.io.DataOutput"] }]
},
{
  "name":"com.ibm.mq.jakarta.jms.MQJMSComponent",
  "methods":[{"name":"<init>","parameterTypes":[] }]
},
{
  "name":"com.ibm.mq.jmqi.internal.charset.HP1051Charset",
  "methods":[{"name":"<init>","parameterTypes":[] }]
},
{
  "name":"com.ibm.mq.jmqi.internal.charset.IBM37Charset",
  "methods":[{"name":"<init>","parameterTypes":[] }]
},
{
  "name":"com.ibm.mq.jmqi.internal.charset.IBM437Charset",
  "methods":[{"name":"<init>","parameterTypes":[] }]
},
{
  "name":"com.ibm.mq.jmqi.internal.charset.IBM500Charset",
  "methods":[{"name":"<init>","parameterTypes":[] }]
},
{
  "name":"com.ibm.mq.jmqi.internal.charset.IBM850Charset",
  "methods":[{"name":"<init>","parameterTypes":[] }]
},
{
  "name":"com.ibm.mq.jmqi.internal.charset.IBM866Charset",
  "methods":[{"name":"<init>","parameterTypes":[] }]
},
{
  "name":"com.ibm.mq.jmqi.internal.charset.IBM930Charset",
  "methods":[{"name":"<init>","parameterTypes":[] }]
},
{
  "name":"com.ibm.mq.jmqi.remote.api.RemoteFAP",
  "methods":[{"name":"<init>","parameterTypes":["com.ibm.mq.jmqi.JmqiEnvironment","int"] }]
},
{
  "name":"com.ibm.msg.client.commonservices.j2se.J2SEComponent",
  "methods":[{"name":"<init>","parameterTypes":[] }]
},
{
  "name":"com.ibm.msg.client.commonservices.propertystore.PropertyStoreControl",
  "queryAllPublicMethods":true
},
{
  "name":"com.ibm.msg.client.commonservices.propertystore.PropertyStoreControlImpl",
  "queryAllPublicConstructors":true
},
{
  "name":"com.ibm.msg.client.jakarta.jms.internal.JMSComponent",
  "methods":[{"name":"<init>","parameterTypes":[] }]
},
{
  "name":"com.ibm.msg.client.jakarta.wmq.factories.WMQComponent",
  "methods":[{"name":"<init>","parameterTypes":[] }]
},
{
  "name":"com.intellij.junit6.JUnit6IdeaTestRunner",
  "methods":[{"name":"<init>","parameterTypes":[] }]
},
{
  "name":"com.intellij.rt.debugger.agent.CaptureStorage",
  "queryAllPublicMethods":true
},
{
  "name":"com.intellij.rt.execution.application.AppMainV2$Agent",
  "methods":[{"name":"premain","parameterTypes":["java.lang.String","java.lang.instrument.Instrumentation"] }]
},
{
  "name":"com.sun.jna.CallbackProxy",
  "methods":[{"name":"callback","parameterTypes":["java.lang.Object[]"] }]
},
{
  "name":"com.sun.jna.Library",
  "allDeclaredClasses":true,
  "queryAllPublicMethods":true
},
{
  "name":"com.sun.jna.Structure",
  "allDeclaredClasses":true,
  "queryAllDeclaredMethods":true,
  "queryAllPublicMethods":true
},
{
  "name":"com.sun.jna.Structure$ByReference",
  "allDeclaredClasses":true,
  "queryAllPublicMethods":true
},
{
  "name":"com.sun.jna.ptr.IntByReference",
  "methods":[{"name":"<init>","parameterTypes":[] }]
},
{
  "name":"com.sun.jna.win32.DLLCallback"
},
{
  "name":"com.sun.management.GarbageCollectorMXBean",
  "queryAllPublicMethods":true
},
{
  "name":"com.sun.management.GcInfo",
  "queryAllPublicMethods":true
},
{
  "name":"com.sun.management.HotSpotDiagnosticMXBean",
  "queryAllPublicMethods":true
},
{
  "name":"com.sun.management.OperatingSystemMXBean",
  "queryAllPublicMethods":true
},
{
  "name":"com.sun.management.ThreadMXBean",
  "queryAllPublicMethods":true
},
{
  "name":"com.sun.management.UnixOperatingSystemMXBean",
  "queryAllPublicMethods":true
},
{
  "name":"com.sun.management.VMOption",
  "queryAllPublicMethods":true
},
{
  "name":"com.sun.management.internal.GarbageCollectorExtImpl",
  "queryAllPublicConstructors":true
},
{
  "name":"com.sun.management.internal.HotSpotDiagnostic",
  "queryAllPublicConstructors":true
},
{
  "name":"com.sun.management.internal.HotSpotThreadImpl",
  "queryAllPublicConstructors":true
},
{
  "name":"com.sun.management.internal.OperatingSystemImpl",
  "queryAllPublicConstructors":true
},
{
  "name":"com.sun.org.apache.xerces.internal.jaxp.SAXParserFactoryImpl",
  "methods":[{"name":"<init>","parameterTypes":[] }]
},
{
  "name":"java.io.DataInputStream"
},
{
  "name":"java.io.FilterInputStream",
  "methods":[{"name":"mark","parameterTypes":["int"] }, {"name":"reset","parameterTypes":[] }]
},
{
  "name":"java.lang.Boolean",
  "fields":[{"name":"TYPE"}]
},
{
  "name":"java.lang.Byte",
  "fields":[{"name":"TYPE"}]
},
{
  "name":"java.lang.Character",
  "fields":[{"name":"TYPE"}]
},
{
  "name":"java.lang.Deprecated",
  "queryAllPublicMethods":true
},
{
  "name":"java.lang.Double",
  "fields":[{"name":"TYPE"}]
},
{
  "name":"java.lang.Float",
  "fields":[{"name":"TYPE"}]
},
{
  "name":"java.lang.Integer",
  "fields":[{"name":"TYPE"}]
},
{
  "name":"java.lang.Long",
  "fields":[{"name":"TYPE"}]
},
{
  "name":"java.lang.Object",
  "methods":[{"name":"equals","parameterTypes":["java.lang.Object"] }, {"name":"hashCode","parameterTypes":[] }, {"name":"toString","parameterTypes":[] }]
},
{
  "name":"java.lang.Short",
  "fields":[{"name":"TYPE"}]
},
{
  "name":"java.lang.StackTraceElement",
  "queryAllPublicMethods":true
},
{
  "name":"java.lang.String",
  "fields":[{"name":"TYPE"}]
},
{
  "name":"java.lang.Thread",
  "fields":[{"name":"threadLocalRandomProbe"}]
},
{
  "name":"java.lang.Throwable",
  "methods":[{"name":"addSuppressed","parameterTypes":["java.lang.Throwable"] }]
},
{
  "name":"java.lang.Void",
  "fields":[{"name":"TYPE"}]
},
{
  "name":"java.lang.invoke.MethodHandle",
  "methods":[{"name":"bindTo","parameterTypes":["java.lang.Object"] }, {"name":"invokeWithArguments","parameterTypes":["java.lang.Object[]"] }]
},
{
  "name":"java.lang.invoke.MethodHandles",
  "methods":[{"name":"lookup","parameterTypes":[] }, {"name":"privateLookupIn","parameterTypes":["java.lang.Class","java.lang.invoke.MethodHandles$Lookup"] }]
},
{
  "name":"java.lang.invoke.MethodHandles$Lookup",
  "methods":[{"name":"findSpecial","parameterTypes":["java.lang.Class","java.lang.String","java.lang.invoke.MethodType","java.lang.Class"] }, {"name":"in","parameterTypes":["java.lang.Class"] }, {"name":"unreflectSpecial","parameterTypes":["java.lang.reflect.Method","java.lang.Class"] }]
},
{
  "name":"java.lang.invoke.MethodType",
  "methods":[{"name":"methodType","parameterTypes":["java.lang.Class","java.lang.Class[]"] }]
},
{
  "name":"java.lang.management.BufferPoolMXBean",
  "queryAllPublicMethods":true
},
{
  "name":"java.lang.management.ClassLoadingMXBean",
  "queryAllPublicMethods":true
},
{
  "name":"java.lang.management.CompilationMXBean",
  "queryAllPublicMethods":true
},
{
  "name":"java.lang.management.LockInfo",
  "queryAllPublicMethods":true
},
{
  "name":"java.lang.management.ManagementPermission",
  "methods":[{"name":"<init>","parameterTypes":["java.lang.String"] }]
},
{
  "name":"java.lang.management.MemoryMXBean",
  "queryAllPublicMethods":true
},
{
  "name":"java.lang.management.MemoryManagerMXBean",
  "queryAllPublicMethods":true
},
{
  "name":"java.lang.management.MemoryPoolMXBean",
  "queryAllPublicMethods":true
},
{
  "name":"java.lang.management.MemoryUsage",
  "queryAllPublicMethods":true
},
{
  "name":"java.lang.management.MonitorInfo",
  "queryAllPublicMethods":true
},
{
  "name":"java.lang.management.PlatformLoggingMXBean",
  "queryAllPublicMethods":true,
  "methods":[{"name":"getLoggerLevel","parameterTypes":["java.lang.String"] }, {"name":"getLoggerNames","parameterTypes":[] }, {"name":"getParentLoggerName","parameterTypes":["java.lang.String"] }, {"name":"setLoggerLevel","parameterTypes":["java.lang.String","java.lang.String"] }]
},
{
  "name":"java.lang.management.RuntimeMXBean",
  "queryAllPublicMethods":true
},
{
  "name":"java.lang.management.ThreadInfo",
  "queryAllPublicMethods":true
},
{
  "name":"java.lang.reflect.Method",
  "methods":[{"name":"isDefault","parameterTypes":[] }, {"name":"isVarArgs","parameterTypes":[] }]
},
{
  "name":"java.math.BigDecimal"
},
{
  "name":"java.math.BigInteger"
},
{
  "name":"java.nio.Buffer"
},
{
  "name":"java.security.SecureRandomParameters"
},
{
  "name":"java.util.Date"
},
{
  "name":"java.util.PropertyPermission",
  "methods":[{"name":"<init>","parameterTypes":["java.lang.String","java.lang.String"] }]
},
{
  "name":"java.util.concurrent.atomic.AtomicBoolean",
  "fields":[{"name":"value"}]
},
{
  "name":"java.util.concurrent.atomic.AtomicReference",
  "fields":[{"name":"value"}]
},
{
  "name":"java.util.concurrent.atomic.Striped64",
  "fields":[{"name":"base"}, {"name":"cellsBusy"}]
},
{
  "name":"java.util.logging.LogManager",
  "methods":[{"name":"getLoggingMXBean","parameterTypes":[] }]
},
{
  "name":"java.util.logging.LoggingMXBean",
  "queryAllPublicMethods":true
},
{
  "name":"javax.management.MBeanOperationInfo",
  "queryAllPublicMethods":true,
  "methods":[{"name":"getSignature","parameterTypes":[] }]
},
{
  "name":"javax.management.MBeanServerBuilder",
  "methods":[{"name":"<init>","parameterTypes":[] }]
},
{
  "name":"javax.management.ObjectName"
},
{
  "name":"javax.management.StandardEmitterMBean",
  "methods":[{"name":"cacheMBeanInfo","parameterTypes":["javax.management.MBeanInfo"] }, {"name":"getCachedMBeanInfo","parameterTypes":[] }, {"name":"getMBeanInfo","parameterTypes":[] }]
},
{
  "name":"javax.management.openmbean.CompositeData"
},
{
  "name":"javax.management.openmbean.OpenMBeanOperationInfoSupport"
},
{
  "name":"javax.management.openmbean.TabularData"
},
{
  "name":"javax.net.ssl.SNIHostName"
},
{
  "name":"jdk.jfr.FlightRecorder"
},
{
  "name":"jdk.management.jfr.ConfigurationInfo",
  "queryAllPublicMethods":true
},
{
  "name":"jdk.management.jfr.EventTypeInfo",
  "queryAllPublicMethods":true
},
{
  "name":"jdk.management.jfr.FlightRecorderMXBean",
  "queryAllPublicMethods":true
},
{
  "name":"jdk.management.jfr.FlightRecorderMXBeanImpl",
  "queryAllPublicConstructors":true,
  "methods":[{"name":"cacheMBeanInfo","parameterTypes":["javax.management.MBeanInfo"] }, {"name":"getCachedMBeanInfo","parameterTypes":[] }, {"name":"getMBeanInfo","parameterTypes":[] }, {"name":"getNotificationInfo","parameterTypes":[] }]
},
{
  "name":"jdk.management.jfr.RecordingInfo",
  "queryAllPublicMethods":true
},
{
  "name":"jdk.management.jfr.SettingDescriptorInfo",
  "queryAllPublicMethods":true
},
{
  "name":"junit.framework.ComparisonFailure"
},
{
  "name":"kotlin.Metadata"
},
{
  "name":"org.apache.maven.surefire.junitplatform.JUnitPlatformProvider",
  "methods":[{"name":"<init>","parameterTypes":["org.apache.maven.surefire.api.provider.ProviderParameters"] }]
},
{
  "name":"org.apiguardian.api.API",
  "queryAllPublicMethods":true
},
{
  "name":"org.junit.internal.AssumptionViolatedException"
},
{
  "name":"org.junit.jupiter.api.Test",
  "queryAllPublicMethods":true
},
{
  "name":"org.junit.platform.commons.annotation.Testable",
  "queryAllPublicMethods":true
},
{
  "name":"org.junit.platform.launcher.LauncherSession",
  "methods":[{"name":"getLauncher","parameterTypes":[] }]
},
{
  "name":"org.junit.platform.launcher.core.LauncherFactory",
  "methods":[{"name":"openSession","parameterTypes":[] }]
},
{
  "name":"sun.management.ClassLoadingImpl",
  "queryAllPublicConstructors":true
},
{
  "name":"sun.management.CompilationImpl",
  "queryAllPublicConstructors":true
},
{
  "name":"sun.management.ManagementFactoryHelper$1",
  "queryAllPublicConstructors":true
},
{
  "name":"sun.management.ManagementFactoryHelper$PlatformLoggingImpl",
  "queryAllPublicConstructors":true
},
{
  "name":"sun.management.MemoryImpl",
  "queryAllPublicConstructors":true
},
{
  "name":"sun.management.MemoryManagerImpl",
  "queryAllPublicConstructors":true
},
{
  "name":"sun.management.MemoryPoolImpl",
  "queryAllPublicConstructors":true
},
{
  "name":"sun.management.RuntimeImpl",
  "queryAllPublicConstructors":true
},
{
  "name":"sun.security.provider.DRBG",
  "methods":[{"name":"<init>","parameterTypes":["java.security.SecureRandomParameters"] }]
},
{
  "name":"sun.security.provider.NativePRNG",
  "methods":[{"name":"<init>","parameterTypes":[] }, {"name":"<init>","parameterTypes":["java.security.SecureRandomParameters"] }]
},
{
  "name":"sun.security.provider.SHA",
  "methods":[{"name":"<init>","parameterTypes":[] }]
},
{
  "name":"sun.security.provider.SHA2$SHA256",
  "methods":[{"name":"<init>","parameterTypes":[] }]
}
]
